examples/__init__.py
examples/run_examples.py
examples/gpa_science_classification/__init__.py
examples/gpa_science_classification/create_spec.py
examples/gpa_science_classification/demo_new_par_method.py
examples/gpa_science_classification/generate_experiment_plots.py
examples/gpa_science_classification/generate_gpa_plots.py
examples/gpa_science_classification/generate_gpa_plots_debug.py
examples/gpa_science_classification/generate_gpa_plots_fairware.py
examples/gpa_science_classification/generate_gpa_plots_forpitchdeck.py
examples/gpa_science_classification/gpa_datasplit.py
examples/gpa_science_classification/run_engine.py
examples/gpa_science_classification/tutorial.py
examples/headless_facial_gender/__init__.py
examples/headless_facial_gender/create_spec.py
examples/headless_facial_gender/full_model.py
examples/headless_facial_gender/generate_experiment_plots.py
examples/headless_facial_gender/headless_model.py
examples/headless_facial_gender/headonly_model.py
examples/headless_facial_gender/process_data.py
examples/headless_facial_race/__init__.py
examples/headless_facial_race/create_spec.py
examples/headless_facial_race/full_model.py
examples/headless_facial_race/generate_experiment_plots.py
examples/headless_facial_race/headless_model.py
examples/headless_facial_race/headonly_model.py
examples/headless_facial_race/process_data.py
examples/headless_mnist/__init__.py
examples/headless_mnist/create_spec.py
examples/headless_mnist/full_model.py
examples/headless_mnist/generate_experiment_plots.py
examples/headless_mnist/headless_model.py
examples/headless_mnist/headonly_model.py
examples/lie_detection/__init__.py
examples/lie_detection/create_spec.py
examples/lie_detection/generate_experiment_plots.py
examples/loans/__init__.py
examples/loans/generate_experiment_plots.py
examples/loans/generate_german_loan_plots.py
examples/loans/generate_german_loan_plots_eqodds.py
examples/loans/generate_german_loan_plots_fairlearn.py
seldonian_experiments-0.2.5.dist-info/LICENSE
seldonian_experiments-0.2.5.dist-info/METADATA
seldonian_experiments-0.2.5.dist-info/WHEEL
seldonian_experiments-0.2.5.dist-info/top_level.txt
seldonian_experiments-0.2.5.dist-info/RECORD
