Metadata-Version: 2.1
Name: seldonian_experiments
Version: 0.2.5
Summary: Library for running experiments with Seldonian algorithms
Home-page: 
Author: Austin Hoag
Author-email: austinthomashoag@gmail.com
Project-URL: Bug Tracker, https://github.com/seldonian-framework/Experiments/issues
Classifier: Programming Language :: Python :: 3
Classifier: License :: OSI Approved :: BSD License
Classifier: Operating System :: OS Independent
Requires-Python: >=3.8
License-File: LICENSE
Requires-Dist: seldonian-engine
